lingerclient/__init__.py
lingerclient/lingerclient.py
lingerclient-1.0.0.dist-info/LICENSE
lingerclient-1.0.0.dist-info/METADATA
lingerclient-1.0.0.dist-info/WHEEL
lingerclient-1.0.0.dist-info/top_level.txt
lingerclient-1.0.0.dist-info/RECORD
